cu_cat/__init__.py
cu_cat/_check_dependencies.py
cu_cat/_datetime_encoder.py
cu_cat/_deduplicate.py
cu_cat/_dep_manager.py
cu_cat/_gap_encoder.py
cu_cat/_table_vectorizer.py
cu_cat/_utils.py
cu_cat/_version.py
cu_cat-0.9.11.dist-info/METADATA
cu_cat-0.9.11.dist-info/WHEEL
cu_cat-0.9.11.dist-info/top_level.txt
cu_cat-0.9.11.dist-info/RECORD
