Metadata-Version: 2.1
Name: cu-cat
Version: 0.9.11
Summary: An end-to-end gpu Python library that encodes categorical variables into machine-learnable numerics
Home-page: https://github.com/graphistry/cu-cat
Download-URL: https://github.com/graphistry/cu-cat
Author: The Graphistry Team
Author-email: pygraphistry@graphistry.com
License: BSD
Keywords: cudf,cuml,GPU,Rapids
Platform: any
Requires-Python: >=3.8
Requires-Dist: numpy
Requires-Dist: pandas
Requires-Dist: setuptools
Requires-Dist: typing-extensions
Requires-Dist: pyarrow >=0.15.0
Requires-Dist: scikit-learn <=1.3.2
Requires-Dist: psutil
Requires-Dist: dirty-cat
Requires-Dist: scipy
Provides-Extra: build
Requires-Dist: build ; extra == 'build'
Provides-Extra: dev
Requires-Dist: pytest ; extra == 'dev'
Requires-Dist: docutils ==0.16 ; extra == 'dev'
Requires-Dist: mock ; extra == 'dev'
Requires-Dist: pandas-stubs ; extra == 'dev'
Requires-Dist: build ; extra == 'dev'
Requires-Dist: flake8 >=5.0 ; extra == 'dev'
Requires-Dist: sphinx-autodoc-typehints ==1.11.1 ; extra == 'dev'
Requires-Dist: sphinx-rtd-theme ==0.5.1 ; extra == 'dev'
Requires-Dist: Jinja2 <3.1 ; extra == 'dev'
Requires-Dist: mypy ; extra == 'dev'
Requires-Dist: sphinx ==3.4.3 ; extra == 'dev'
Requires-Dist: numba >=0.57.1 ; extra == 'dev'
Requires-Dist: tqdm-stubs ; extra == 'dev'
Requires-Dist: ipython ; extra == 'dev'
Requires-Dist: types-requests ; extra == 'dev'
Provides-Extra: docs
Requires-Dist: sphinx ==3.4.3 ; extra == 'docs'
Requires-Dist: docutils ==0.16 ; extra == 'docs'
Requires-Dist: sphinx-autodoc-typehints ==1.11.1 ; extra == 'docs'
Requires-Dist: sphinx-rtd-theme ==0.5.1 ; extra == 'docs'
Requires-Dist: Jinja2 <3.1 ; extra == 'docs'
Provides-Extra: test
Requires-Dist: flake8 >=5.0 ; extra == 'test'
Requires-Dist: mock ; extra == 'test'
Requires-Dist: mypy ; extra == 'test'
Requires-Dist: pytest ; extra == 'test'
Requires-Dist: pandas-stubs ; extra == 'test'
Requires-Dist: types-requests ; extra == 'test'
Requires-Dist: ipython ; extra == 'test'
Requires-Dist: tqdm-stubs ; extra == 'test'
Provides-Extra: testai
Requires-Dist: numba >=0.57.1 ; extra == 'testai'
